NL2SQLEvaluator/__init__.py
NL2SQLEvaluator/cli.py
NL2SQLEvaluator/config.py
NL2SQLEvaluator/hf_parser.py
NL2SQLEvaluator/logger.py
NL2SQLEvaluator/node_registry.py
NL2SQLEvaluator/pipeline.py
NL2SQLEvaluator/dataset_reader_nodes/__init__.py
NL2SQLEvaluator/dataset_reader_nodes/bird_reader.py
NL2SQLEvaluator/dataset_reader_nodes/data_reader_protocol.py
NL2SQLEvaluator/db_executor_nodes/__init__.py
NL2SQLEvaluator/db_executor_nodes/db_executor_protocol.py
NL2SQLEvaluator/db_executor_nodes/sqlite_db_executor.py
NL2SQLEvaluator/db_executor_nodes/cache/__init__.py
NL2SQLEvaluator/db_executor_nodes/cache/cache_protocol.py
NL2SQLEvaluator/db_executor_nodes/cache/sqlite_cache.py
NL2SQLEvaluator/evaluator_nodes/__init__.py
NL2SQLEvaluator/evaluator_nodes/bird_ex_evaluator.py
NL2SQLEvaluator/evaluator_nodes/evaluator_protocol.py
NL2SQLEvaluator/evaluator_nodes/ex_with_card.py
NL2SQLEvaluator/evaluator_nodes/qatch_metrics.py
NL2SQLEvaluator/evaluator_nodes/utils.py
NL2SQLEvaluator/predictor_nodes/__init__.py
NL2SQLEvaluator/predictor_nodes/litellm_predictor.py
NL2SQLEvaluator/predictor_nodes/predictor_protocol.py
NL2SQLEvaluator/predictor_nodes/vllm_predictor.py
NL2SQLEvaluator/saver_nodes/__init__.py
NL2SQLEvaluator/saver_nodes/json_saver.py
NL2SQLEvaluator/saver_nodes/saver_protocol.py
nl2sqlevaluator-1.3.4.dist-info/METADATA
nl2sqlevaluator-1.3.4.dist-info/WHEEL
nl2sqlevaluator-1.3.4.dist-info/entry_points.txt
nl2sqlevaluator-1.3.4.dist-info/licenses/LICENSE
nl2sqlevaluator-1.3.4.dist-info/RECORD
