Metadata-Version: 2.4
Name: NL2SQLEvaluator
Version: 1.3.4
Summary: Add your description here
License-File: LICENSE
Requires-Python: <3.13,>=3.12
Requires-Dist: bm25s>=0.2.14
Requires-Dist: datasets>=4.0.0
Requires-Dist: fastparquet>=2024.11.0
Requires-Dist: func-timeout>=4.3.5
Requires-Dist: loguru>=0.7.3
Requires-Dist: pandas>=2.3.2
Requires-Dist: pyarrow>=21.0.0
Requires-Dist: pydantic>=2.11.7
Requires-Dist: python-dotenv>=1.1.1
Requires-Dist: sqlglot>=27.11.0
Requires-Dist: tqdm>=4.67.1
Requires-Dist: typer-config[all]>=1.4.2
Requires-Dist: typer>=0.20.0
Requires-Dist: wandb>=0.21.3
